morphomics/__init__.py
morphomics/default_parameters.py
morphomics/protocols.py
morphomics/utils.py
morphomics/Analysis/bootstrapping.py
morphomics/Analysis/mapping.py
morphomics/Analysis/morphometrics.py
morphomics/Analysis/plotting.py
morphomics/Analysis/reduction.py
morphomics/Neuron/Neuron.py
morphomics/Neuron/__init__.py
morphomics/Neuron/methods.py
morphomics/Population/Population.py
morphomics/Population/__init__.py
morphomics/Soma/Soma.py
morphomics/Soma/__init__.py
morphomics/Soma/methods.py
morphomics/TMD_view/__init__.py
morphomics/TMD_view/common.py
morphomics/TMD_view/plot.py
morphomics/TMD_view/view.py
morphomics/Topology/__init__.py
morphomics/Topology/analysis.py
morphomics/Topology/methods.py
morphomics/Topology/persistent_properties.py
morphomics/Topology/transformations.py
morphomics/Tree/Tree.py
morphomics/Tree/__init__.py
morphomics/Tree/methods.py
morphomics/io/__init__.py
morphomics/io/io.py
morphomics/io/neuromorpho.py
morphomics/io/swc.py
Morphomics-2.0.7.dist-info/AUTHORS.md
Morphomics-2.0.7.dist-info/LICENSE
Morphomics-2.0.7.dist-info/METADATA
Morphomics-2.0.7.dist-info/WHEEL
Morphomics-2.0.7.dist-info/top_level.txt
Morphomics-2.0.7.dist-info/RECORD
