Metadata-Version: 2.1
Name: Morphomics
Version: 2.0.7
Summary: morphOMICs: a python package for the topological and statistical  analysis of microglia morphology (appliable to any cell structure)
Home-page: https://github.com/siegert-lab/morphOMICs
Author: Amin Alam, Ryan Cubero
License: GNU
Keywords: Morhpomics,MicroGlia,UMAP,TDA,Topological Data Analysis,Microscopy,Image Analysis,Cell Morphology
Requires-Python: <=3.10
License-File: LICENSE
License-File: AUTHORS.md
Requires-Dist: scipy
Requires-Dist: pandas
Requires-Dist: scikit-learn
Requires-Dist: matplotlib
Requires-Dist: tomli
Requires-Dist: networkx
Requires-Dist: Cython
Requires-Dist: pickle4
Requires-Dist: h5py >=2.8.0
Requires-Dist: scipy >=0.13.3
Requires-Dist: numpy <1.25
Requires-Dist: enum34 >=1.0.4
Requires-Dist: scikit-learn >=0.19.1
Requires-Dist: matplotlib >=3.2.0
Requires-Dist: umap-learn >=0.3.10
Requires-Dist: ipyvolume >=0.6.1
Requires-Dist: morphon >=0.0.8
Requires-Dist: pylmeasure >=0.2.0
Requires-Dist: ipython-genutils
Requires-Dist: fa2-modified
